pheatmap/__init__.py
pheatmap/_annotation.py
pheatmap/_heatmap.py
pheatmap/_layout.py
pheatmap/_legend.py
pheatmap/_pheatmap.py
pheatmap/_utils.py
pheatmap-1.0.1.dist-info/LICENSE
pheatmap-1.0.1.dist-info/METADATA
pheatmap-1.0.1.dist-info/WHEEL
pheatmap-1.0.1.dist-info/top_level.txt
pheatmap-1.0.1.dist-info/RECORD
