Metadata-Version: 2.1
Name: pheatmap
Version: 1.0.1
Summary: pheatmap for Python
Home-page: https://github.com/Ann-Holmes/pheatmap
Author: Zongliang Hou
Author-email: zonglianghou@163.com
Project-URL: Documents, https://pheatmap.readthedocs.io/en/latest/
Project-URL: Bug Reports, https://github.com/Ann-Holmes/pheatmap/issues
Project-URL: Source, https://github.com/Ann-Holmes/pheatmap
Keywords: heatmap,gene,expression,visualization
Classifier: Intended Audience :: Education
Classifier: Intended Audience :: Science/Research
Classifier: Topic :: Scientific/Engineering :: Bio-Informatics
Classifier: License :: OSI Approved :: BSD License
Classifier: Programming Language :: Python :: 3
Classifier: Programming Language :: Python :: 3.8
Classifier: Programming Language :: Python :: 3.9
Classifier: Programming Language :: Python :: 3.10
Classifier: Programming Language :: Python :: 3 :: Only
Classifier: Operating System :: POSIX :: Linux
Requires-Python: >=3.8, <4
License-File: LICENSE
Requires-Dist: numpy
Requires-Dist: matplotlib
Requires-Dist: pandas
Provides-Extra: dev
Requires-Dist: sphinx ; extra == 'dev'
Requires-Dist: myst-parser ; extra == 'dev'
